psvr2toolkit_installer/__init__.py
psvr2toolkit_installer/__main__.py
psvr2toolkit_installer/github.py
psvr2toolkit_installer/helpers.py
psvr2toolkit_installer/vars.py
psvr2toolkit_installer-1.1.1.dist-info/entry_points.txt
psvr2toolkit_installer-1.1.1.dist-info/licenses/LICENSE
psvr2toolkit_installer-1.1.1.dist-info/WHEEL
psvr2toolkit_installer-1.1.1.dist-info/METADATA
psvr2toolkit_installer-1.1.1.dist-info/RECORD
