Metadata-Version: 2.4
Name: psvr2toolkit-installer
Version: 1.1.1
Summary: An unofficial tool that can install and configure the PlayStation VR2 Toolkit.
Requires-Python: >= 3.14
License-File: LICENSE
Requires-Dist: SteamPathFinder
Requires-Dist: aiofiles
Requires-Dist: githubkit
Requires-Dist: nicegui
Requires-Dist: pywebview
Requires-Dist: signify
Project-URL: Funding, https://ko-fi.com/maidscientistizutsumimarin
Project-URL: Source, https://github.com/MaidScientistIzutsumiMarin/psvr2toolkit-installer
